[
  {
    "URL": "https://dask.org",
    "author": [
      {
        "literal": "Dask Development Team"
      }
    ],
    "id": "hj1CnyWB",
    "issued": {
      "date-parts": [
        [
          2016
        ]
      ]
    },
    "title": "Dask: Library for dynamic task scheduling",
    "title-short": "Dask",
    "type": "book",
    "note": "Loaded from an external bibliography file by Manubot.\nsource_bibliography: manual-references.bib\nstandard_id: dask"
  },
  {
    "publisher": "Springer Science and Business Media LLC",
    "issue": "1",
    "abstract": "<jats:title>Abstract</jats:title><jats:p>We present Biomedisa, a free and easy-to-use open-source online platform developed for semi-automatic segmentation of large volumetric images. The segmentation is based on a smart interpolation of sparsely pre-segmented slices taking into account the complete underlying image data. Biomedisa is particularly valuable when little a priori knowledge is available, e.g. for the dense annotation of the training data for a deep neural network. The platform is accessible through a web browser and requires no complex and tedious configuration of software and model parameters, thus addressing the needs of scientists without substantial computational expertise. We demonstrate that Biomedisa can drastically reduce both the time and human effort required to segment large images. It achieves a significant improvement over the conventional approach of densely pre-segmented slices with subsequent morphological interpolation as well as compared to segmentation tools that also consider the underlying image data. Biomedisa can be used for different 3D imaging modalities and various biomedical applications.</jats:p>",
    "DOI": "10.1038/s41467-020-19303-w",
    "type": "article-journal",
    "source": "Crossref",
    "title": "Introducing Biomedisa as an open-source online platform for biomedical image segmentation",
    "volume": "11",
    "author": [
      {
        "given": "Philipp D.",
        "family": "Lösel"
      },
      {
        "given": "Thomas",
        "family": "van de Kamp"
      },
      {
        "given": "Alejandra",
        "family": "Jayme"
      },
      {
        "given": "Alexey",
        "family": "Ershov"
      },
      {
        "given": "Tomáš",
        "family": "Faragó"
      },
      {
        "given": "Olaf",
        "family": "Pichler"
      },
      {
        "given": "Nicholas",
        "family": "Tan Jerome"
      },
      {
        "given": "Narendar",
        "family": "Aadepu"
      },
      {
        "given": "Sabine",
        "family": "Bremer"
      },
      {
        "given": "Suren A.",
        "family": "Chilingaryan"
      },
      {
        "given": "Michael",
        "family": "Heethoff"
      },
      {
        "given": "Andreas",
        "family": "Kopmann"
      },
      {
        "given": "Janes",
        "family": "Odar"
      },
      {
        "given": "Sebastian",
        "family": "Schmelzle"
      },
      {
        "given": "Marcus",
        "family": "Zuber"
      },
      {
        "given": "Joachim",
        "family": "Wittbrodt"
      },
      {
        "given": "Tilo",
        "family": "Baumbach"
      },
      {
        "given": "Vincent",
        "family": "Heuveline"
      }
    ],
    "container-title": "Nature Communications",
    "language": "en",
    "issued": {
      "date-parts": [
        [
          2020,
          11,
          4
        ]
      ]
    },
    "URL": "https://doi.org/gh58qn",
    "container-title-short": "Nat Commun",
    "PMCID": "PMC7642381",
    "PMID": "33149150",
    "id": "jHalJ9Zw",
    "note": "This CSL Item was generated by Manubot v0.6.1 from its persistent identifier (standard_id).\nstandard_id: doi:10.1038/s41467-020-19303-w"
  },
  {
    "publisher": "Oxford University Press (OUP)",
    "issue": "1",
    "abstract": "<jats:title>Synopsis</jats:title><jats:p>The increased use of imaging technology in biological research has drastically altered morphological studies in recent decades and allowed for the preservation of important collection specimens alongside detailed visualization of bony and soft-tissue structures. Despite the benefits associated with these newer imaging techniques, there remains a need for more “traditional” methods of morphological examination in many comparative studies. In this paper, we describe the costs and benefits of the various methods of visualizing, examining, and comparing morphological structures. There are significant differences not only in the costs associated with these different methods (monetary, time, equipment, and software), but also in the degree to which specimens are destroyed. We argue not for any one particular method over another in morphological studies, but instead suggest a combination of methods is useful not only for breadth of visualization, but also for the financial and time constraints often imposed on early-career research scientists.</jats:p>",
    "DOI": "10.1093/iob/obad008",
    "type": "article-journal",
    "source": "Crossref",
    "title": "A New Era of Morphological Investigations: Reviewing Methods for Comparative Anatomical Studies",
    "volume": "5",
    "author": [
      {
        "given": "K L",
        "family": "Ford"
      },
      {
        "given": "J S",
        "family": "Albert"
      },
      {
        "given": "A P",
        "family": "Summers"
      },
      {
        "given": "B P",
        "family": "Hedrick"
      },
      {
        "given": "E R",
        "family": "Schachner"
      },
      {
        "given": "A S",
        "family": "Jones"
      },
      {
        "given": "K",
        "family": "Evans"
      },
      {
        "given": "P",
        "family": "Chakrabarty"
      }
    ],
    "container-title": "Integrative Organismal Biology",
    "language": "en",
    "issued": {
      "date-parts": [
        [
          2023
        ]
      ]
    },
    "URL": "https://doi.org/grx5rb",
    "PMCID": "PMC10081917",
    "PMID": "37035037",
    "id": "19h9vxsYG",
    "note": "This CSL Item was generated by Manubot v0.6.1 from its persistent identifier (standard_id).\nstandard_id: doi:10.1093/iob/obad008"
  },
  {
    "publisher": "Springer Science and Business Media LLC",
    "issue": "1",
    "abstract": "<jats:title>Abstract</jats:title><jats:p>Recent developments within micro-computed tomography (μCT) imaging have combined to extend our capacity to image tissue in three (3D) and four (4D) dimensions at micron and sub-micron spatial resolutions, opening the way for virtual histology, live cell imaging, subcellular imaging and correlative microscopy. Pivotal to this has been the development of methods to extend the contrast achievable for soft tissue. Herein, we review the new capabilities within the field of life sciences imaging, and consider how future developments in this field could further benefit the life sciences community.</jats:p>",
    "DOI": "10.1186/s12915-020-0753-2",
    "type": "article-journal",
    "source": "Crossref",
    "title": "X-ray computed tomography in life sciences",
    "volume": "18",
    "author": [
      {
        "given": "Shelley D.",
        "family": "Rawson"
      },
      {
        "given": "Jekaterina",
        "family": "Maksimcuka"
      },
      {
        "given": "Philip J.",
        "family": "Withers"
      },
      {
        "given": "Sarah H.",
        "family": "Cartmell"
      }
    ],
    "container-title": "BMC Biology",
    "language": "en",
    "issued": {
      "date-parts": [
        [
          2020,
          2,
          27
        ]
      ]
    },
    "URL": "https://doi.org/ggrx9x",
    "container-title-short": "BMC Biol",
    "PMCID": "PMC7045626",
    "PMID": "32103752",
    "id": "IKVBgaCE",
    "note": "This CSL Item was generated by Manubot v0.6.1 from its persistent identifier (standard_id).\nstandard_id: doi:10.1186/s12915-020-0753-2"
  },
  {
    "publisher": "Public Library of Science (PLoS)",
    "issue": "6",
    "DOI": "10.1371/journal.pcbi.1007128",
    "type": "article-journal",
    "page": "e1007128",
    "source": "Crossref",
    "title": "Open collaborative writing with Manubot",
    "volume": "15",
    "author": [
      {
        "given": "Daniel S.",
        "family": "Himmelstein"
      },
      {
        "given": "Vincent",
        "family": "Rubinetti"
      },
      {
        "given": "David R.",
        "family": "Slochower"
      },
      {
        "given": "Dongbo",
        "family": "Hu"
      },
      {
        "given": "Venkat S.",
        "family": "Malladi"
      },
      {
        "given": "Casey S.",
        "family": "Greene"
      },
      {
        "given": "Anthony",
        "family": "Gitter"
      }
    ],
    "container-title": "PLOS Computational Biology",
    "language": "en",
    "editor": [
      {
        "given": "Dina",
        "family": "Schneidman-Duhovny"
      }
    ],
    "issued": {
      "date-parts": [
        [
          2019,
          6,
          24
        ]
      ]
    },
    "URL": "https://doi.org/c7np",
    "container-title-short": "PLoS Comput Biol",
    "PMCID": "PMC6611653",
    "PMID": "31233491",
    "id": "YuJbg3zO",
    "note": "This CSL Item was generated by Manubot v0.6.1 from its persistent identifier (standard_id).\nstandard_id: doi:10.1371/journal.pcbi.1007128"
  },
  {
    "publisher": "IOS Press",
    "abstract": "<jats:p>It is increasingly necessary for researchers in all fields to write computer code, and in order to reproduce research results, it is important that this code is published. We present Jupyter notebooks, a document format for publishing code, results and explanations in a form that is both readable and executable. We discuss various tools and use cases for notebook documents.</jats:p>",
    "DOI": "10.3233/978-1-61499-649-1-87",
    "type": "chapter",
    "source": "Crossref",
    "title": "Jupyter Notebooks &amp;ndash; a publishing format for reproducible computational workflows",
    "author": [
      {
        "family": "Kluyver Thomas"
      },
      {
        "family": "Ragan-Kelley Benjamin"
      },
      {
        "family": "P&eacute;rez Fernando"
      },
      {
        "family": "Granger Brian"
      },
      {
        "family": "Bussonnier Matthias"
      },
      {
        "family": "Frederic Jonathan"
      },
      {
        "family": "Kelley Kyle"
      },
      {
        "family": "Hamrick Jessica"
      },
      {
        "family": "Grout Jason"
      },
      {
        "family": "Corlay Sylvain"
      },
      {
        "family": "Ivanov Paul"
      },
      {
        "family": "Avila Dami&aacute;n"
      },
      {
        "family": "Abdalla Safia"
      },
      {
        "family": "Willing Carol"
      },
      {
        "family": "Jupyter Development Team"
      }
    ],
    "container-title": "Positioning and Power in Academic Publishing: Players, Agents and Agendas",
    "issued": {
      "date-parts": [
        [
          2016
        ]
      ]
    },
    "URL": "https://doi.org/gf48c9",
    "id": "1Bh7g5XAe",
    "note": "This CSL Item was generated by Manubot v0.6.1 from its persistent identifier (standard_id).\nstandard_id: doi:10.3233/978-1-61499-649-1-87"
  },
  {
    "publisher": "NISO",
    "DOI": "10.3789/ansi.niso.z39.104-2022",
    "type": "entry",
    "source": "Crossref",
    "title": "ANSI/NISO Z39.104-2022, CRediT, Contributor Roles Taxonomy",
    "author": [
      {}
    ],
    "issued": {},
    "URL": "https://doi.org/gqx265",
    "id": "11ofsO2hq",
    "note": "This CSL Item was generated by Manubot v0.6.1 from its persistent identifier (standard_id).\nstandard_id: doi:10.3789/ansi.niso.z39.104-2022"
  },
  {
    "type": "book",
    "id": "4vi5Vvpx",
    "author": [
      {
        "family": "David Haberthür"
      }
    ],
    "issued": {
      "date-parts": [
        [
          2026,
          1,
          15
        ]
      ]
    },
    "abstract": "Datawrangling tomographic scans of sticklebacks for the https://alaskastickleback.com/genomics project",
    "DOI": "10.5281/zenodo.18257528",
    "publisher": "Zenodo",
    "title": "habi/sticklebacks: Maintenance release",
    "URL": "https://doi.org/hbj4g5",
    "version": "0.99",
    "note": "This CSL Item was generated by Manubot v0.6.1 from its persistent identifier (standard_id).\nstandard_id: doi:10.5281/zenodo.18257528"
  },
  {
    "type": "book",
    "id": "115PPSuQp",
    "author": [
      {
        "family": "Haberthür",
        "given": "David"
      }
    ],
    "issued": {
      "date-parts": [
        [
          2019,
          3,
          8
        ]
      ]
    },
    "abstract": "A collection of microtomography sample holders, generated with OpenSCAD",
    "DOI": "10.5281/zenodo.2587555",
    "publisher": "Zenodo",
    "title": "TomoGraphics/Hol3Drs: A release",
    "URL": "https://doi.org/gg9fxh",
    "version": "v0.618",
    "note": "This CSL Item was generated by Manubot v0.6.1 from its persistent identifier (standard_id).\nstandard_id: doi:10.5281/zenodo.2587555"
  },
  {
    "type": "book",
    "id": "p38Gm1rT",
    "author": [
      {
        "family": "Miles",
        "given": "Alistair"
      },
      {
        "family": "Kirkham",
        "given": "John"
      },
      {
        "family": "Durant",
        "given": "Martin"
      },
      {
        "family": "Bourbeau",
        "given": "James"
      },
      {
        "family": "Onalan",
        "given": "Tarik"
      },
      {
        "family": "Hamman",
        "given": "Joe"
      },
      {
        "literal": "Zain Patel"
      },
      {
        "literal": "Shikharsg"
      },
      {
        "family": "Rocklin",
        "given": "Matthew"
      },
      {
        "family": "Dussin",
        "given": "Raphael"
      },
      {
        "family": "Schut",
        "given": "Vincent"
      },
      {
        "family": "Andrade",
        "given": "Elliott Sales De"
      },
      {
        "family": "Abernathey",
        "given": "Ryan"
      },
      {
        "family": "Noyes",
        "given": "Charles"
      },
      {
        "literal": "Sbalmer"
      },
      {
        "literal": "Pyup.Io Bot"
      },
      {
        "family": "Tran",
        "given": "Tommy"
      },
      {
        "family": "Saalfeld",
        "given": "Stephan"
      },
      {
        "family": "Swaney",
        "given": "Justin"
      },
      {
        "family": "Moore",
        "given": "Josh"
      },
      {
        "family": "Jevnik",
        "given": "Joe"
      },
      {
        "family": "Kelleher",
        "given": "Jerome"
      },
      {
        "family": "Funke",
        "given": "Jan"
      },
      {
        "family": "Sakkis",
        "given": "George"
      },
      {
        "family": "Barnes",
        "given": "Chris"
      },
      {
        "family": "Banihirwe",
        "given": "Anderson"
      }
    ],
    "issued": {
      "date-parts": [
        [
          2020,
          1,
          11
        ]
      ]
    },
    "abstract": "See release notes.",
    "DOI": "10.5281/zenodo.3773450",
    "publisher": "Zenodo",
    "title": "zarr-developers/zarr-python: v2.4.0",
    "URL": "https://doi.org/grbf32",
    "version": "v2.4.0",
    "note": "This CSL Item was generated by Manubot v0.6.1 from its persistent identifier (standard_id).\nstandard_id: doi:10.5281/zenodo.3773450"
  },
  {
    "volume": "17",
    "issue": "5",
    "page-first": "713",
    "container-title": "Journal of Information Science and Engineering",
    "author": [
      {
        "literal": "廖炳松"
      },
      {
        "literal": "陳澤生"
      },
      {
        "literal": "詹寶珠"
      }
    ],
    "language": "en",
    "abstract": "",
    "type": "article-journal",
    "title": "A Fast Algorithm for Multilevel Thresholding",
    "issued": {
      "date-parts": [
        [
          "2001",
          "9",
          "1"
        ]
      ]
    },
    "URL": "https://doi.org/hbrn6v",
    "DOI": "10.6688/jise.2001.17.5.1",
    "id": "JICzDA7P",
    "note": "This CSL Item was generated by Manubot v0.6.1 from its persistent identifier (standard_id).\nstandard_id: doi:10.6688/jise.2001.17.5.1"
  },
  {
    "id": "jxVw2kt2",
    "type": "webpage",
    "title": "Overview — K3D-jupyter documentation",
    "URL": "https://k3d-jupyter.org/",
    "accessed": {
      "date-parts": [
        [
          "2026",
          3,
          12
        ]
      ]
    },
    "note": "This CSL Item was generated by Manubot v0.6.1 from its persistent identifier (standard_id).\nstandard_id: url:https://k3d-jupyter.org"
  }
]
